knivesout/__init__.py
knivesout/config.py
knivesout/knivesout.py
knivesout/state.py
knivesout/utils.py
knivesout-23.9.13.11.dist-info/METADATA
knivesout-23.9.13.11.dist-info/WHEEL
knivesout-23.9.13.11.dist-info/entry_points.txt
knivesout-23.9.13.11.dist-info/top_level.txt
knivesout-23.9.13.11.dist-info/RECORD
