Metadata-Version: 2.1
Name: knivesout
Version: 23.9.13.11
Summary: ok
Home-page: https://github.com/private_repo/
Author: slipper
Author-email: r2fscg@gmail.com
Classifier: Programming Language :: Python :: 3
Classifier: License :: OSI Approved :: MIT License
Classifier: Operating System :: OS Independent
Requires-Dist: fire
Requires-Dist: pandas
Requires-Dist: codefast (>=0.9.9)
Requires-Dist: pydantic
